VisualShape3D/Polygons.py
VisualShape3D/Shape3D.py
VisualShape3D/Visual.py
VisualShape3D/__init__.py
VisualShape3D/examples.py
VisualShape3D/geomutils.py
VisualShape3D/mathutils.py
VisualShape3D/plotable.py
test/__init__.py
test/from VisualShape3D.Shape3D import Shape.py
VisualShape3D-1.1.8.dist-info/LICENSE
VisualShape3D-1.1.8.dist-info/METADATA
VisualShape3D-1.1.8.dist-info/WHEEL
VisualShape3D-1.1.8.dist-info/top_level.txt
VisualShape3D-1.1.8.dist-info/RECORD
