Metadata-Version: 2.1
Name: VisualShape3D
Version: 1.1.8
Summary: A package of creating a visible 3D polygon with its dimensions as well as its orietation
Author: Liqun He
Author-email: heliqun@ustc.edu.cn
Classifier: Programming Language :: Python :: 3
Classifier: License :: OSI Approved :: MIT License
Classifier: Operating System :: OS Independent
Requires-Python: >=3.6
License-File: LICENSE
Requires-Dist: numpy
Requires-Dist: pandas
Requires-Dist: matplotlib
